{"v":5,"entries":{"standalone-blockquote--blockquote":{"type":"story","id":"standalone-blockquote--blockquote","name":"Blockquote","title":"Standalone/Blockquote","importPath":"./src/components/Blockquote.stories.tsx","componentPath":"./src/components/Blockquote.tsx","tags":["dev","test"]},"standalone-codeblock--single":{"type":"story","id":"standalone-codeblock--single","name":"Single","title":"Standalone/CodeBlock","importPath":"./src/components/CodeBlock.stories.tsx","componentPath":"./src/components/CodeBlock","tags":["dev","test"]},"standalone-codeblock--multi":{"type":"story","id":"standalone-codeblock--multi","name":"Multi","title":"Standalone/CodeBlock","importPath":"./src/components/CodeBlock.stories.tsx","componentPath":"./src/components/CodeBlock","tags":["dev","test"]},"standalone-codeblock--minimal":{"type":"story","id":"standalone-codeblock--minimal","name":"Minimal","title":"Standalone/CodeBlock","importPath":"./src/components/CodeBlock.stories.tsx","componentPath":"./src/components/CodeBlock","tags":["dev","test"]},"standalone-copyabletext--copyable-text":{"type":"story","id":"standalone-copyabletext--copyable-text","name":"Copyable Text","title":"Standalone/CopyableText","importPath":"./src/components/CopyableText.stories.tsx","componentPath":"./src/components/CopyableText.tsx","tags":["dev","test"]},"standalone-inlinecode--inline-code":{"type":"story","id":"standalone-inlinecode--inline-code","name":"Inline Code","title":"Standalone/InlineCode","importPath":"./src/components/InlineCode.stories.tsx","tags":["dev","test"]},"standalone-internallink--internal-link":{"type":"story","id":"standalone-internallink--internal-link","name":"Internal Link","title":"Standalone/InternalLink","importPath":"./src/components/InternalLink.stories.tsx","tags":["dev","test"]},"standalone-smarttextlink--smart-text-link":{"type":"story","id":"standalone-smarttextlink--smart-text-link","name":"Smart Text Link","title":"Standalone/SmartTextLink","importPath":"./src/components/SmartTextLink.stories.tsx","tags":["dev","test"]},"standalone-table--defaults":{"type":"story","id":"standalone-table--defaults","name":"Defaults","title":"Standalone/Table","importPath":"./src/components/Table.stories.tsx","componentPath":"./src/components/Table.tsx","tags":["dev","test"]},"standalone-table--stripe":{"type":"story","id":"standalone-table--stripe","name":"Stripe","title":"Standalone/Table","importPath":"./src/components/Table.stories.tsx","componentPath":"./src/components/Table.tsx","tags":["dev","test"]},"standalone-table--subtle":{"type":"story","id":"standalone-table--subtle","name":"Subtle","title":"Standalone/Table","importPath":"./src/components/Table.stories.tsx","componentPath":"./src/components/Table.tsx","tags":["dev","test"]}}}